[{"author":{"id":"U_kgDOB_qn0g","is_bot":false,"login":"Jhon-Crow","name":"Jhon-Crow"},"closedAt":null,"createdAt":"2026-01-18T03:15:29Z","labels":[],"number":105,"state":"OPEN","title":"добавь проверку, весь ли функционал сохранён в exe"},{"author":{"id":"U_kgDOB_qn0g","is_bot":false,"login":"Jhon-Crow","name":"Jhon-Crow"},"closedAt":null,"createdAt":"2026-01-18T02:44:40Z","labels":[],"number":103,"state":"OPEN","title":"улучшить систему перемещения"},{"author":{"id":"U_kgDOB_qn0g","is_bot":false,"login":"Jhon-Crow","name":"Jhon-Crow"},"closedAt":null,"createdAt":"2026-01-18T02:18:26Z","labels":[],"number":101,"state":"OPEN","title":"fix COMBAT ai"},{"author":{"id":"U_kgDOB_qn0g","is_bot":false,"login":"Jhon-Crow","name":"Jhon-Crow"},"closedAt":"2026-01-18T02:46:26Z","createdAt":"2026-01-18T01:53:48Z","labels":[],"number":100,"state":"CLOSED","title":"добавь 100% покрытие тестами"},{"author":{"id":"U_kgDOB_qn0g","is_bot":false,"login":"Jhon-Crow","name":"Jhon-Crow"},"closedAt":null,"createdAt":"2026-01-18T01:21:55Z","labels":[],"number":99,"state":"OPEN","title":"update ai групповая тактика"},{"author":{"id":"U_kgDOB_qn0g","is_bot":false,"login":"Jhon-Crow","name":"Jhon-Crow"},"closedAt":null,"createdAt":"2026-01-18T01:18:33Z","labels":[],"number":98,"state":"OPEN","title":"update ai враги должны перемещаться тактически"},{"author":{"id":"U_kgDOB_qn0g","is_bot":false,"login":"Jhon-Crow","name":"Jhon-Crow"},"closedAt":null,"createdAt":"2026-01-18T01:07:03Z","labels":[],"number":97,"state":"OPEN","title":"добавить модель штурмовой винтовки"},{"author":{"id":"U_kgDOB_qn0g","is_bot":false,"login":"Jhon-Crow","name":"Jhon-Crow"},"closedAt":null,"createdAt":"2026-01-18T01:00:05Z","labels":[],"number":96,"state":"OPEN","title":"добавить модель игрока"},{"author":{"id":"U_kgDOB_qn0g","is_bot":false,"login":"Jhon-Crow","name":"Jhon-Crow"},"closedAt":"2026-01-18T02:17:08Z","createdAt":"2026-01-17T23:16:22Z","labels":[],"number":94,"state":"CLOSED","title":"fix ai в состоянии COMBAT враги периодически пытаются стрелять сквозь стену"},{"author":{"id":"U_kgDOB_qn0g","is_bot":false,"login":"Jhon-Crow","name":"Jhon-Crow"},"closedAt":null,"createdAt":"2026-01-17T22:56:06Z","labels":[],"number":93,"state":"OPEN","title":"fix ai при PERSUING состоянии застревают за последним укрытием"},{"author":{"id":"U_kgDOB_qn0g","is_bot":false,"login":"Jhon-Crow","name":"Jhon-Crow"},"closedAt":"2026-01-17T23:12:47Z","createdAt":"2026-01-17T22:23:21Z","labels":[],"number":91,"state":"CLOSED","title":"fix ai при FLANKING состоянии враг может идти в стену"},{"author":{"id":"U_kgDOB_qn0g","is_bot":false,"login":"Jhon-Crow","name":"Jhon-Crow"},"closedAt":null,"createdAt":"2026-01-17T22:17:58Z","labels":[],"number":90,"state":"OPEN","title":"fix ai если противник видит, пули игрока, он должен менять состояние на подходящее"},{"author":{"id":"U_kgDOB_qn0g","is_bot":false,"login":"Jhon-Crow","name":"Jhon-Crow"},"closedAt":"2026-01-17T22:51:35Z","createdAt":"2026-01-17T21:46:29Z","labels":[],"number":88,"state":"CLOSED","title":"fix combat состояние ai"},{"author":{"id":"U_kgDOB_qn0g","is_bot":false,"login":"Jhon-Crow","name":"Jhon-Crow"},"closedAt":null,"createdAt":"2026-01-12T23:19:39Z","labels":[],"number":86,"state":"OPEN","title":"fix магазины"},{"author":{"id":"U_kgDOB_qn0g","is_bot":false,"login":"Jhon-Crow","name":"Jhon-Crow"},"closedAt":"2026-01-17T21:24:25Z","createdAt":"2026-01-12T23:09:27Z","labels":[],"number":85,"state":"CLOSED","title":"добавь дебаг надпись над врагами"},{"author":{"id":"U_kgDOB_qn0g","is_bot":false,"login":"Jhon-Crow","name":"Jhon-Crow"},"closedAt":null,"createdAt":"2026-01-12T22:42:19Z","labels":[],"number":84,"state":"OPEN","title":"добавить систему распространения звука"},{"author":{"id":"U_kgDOB_qn0g","is_bot":false,"login":"Jhon-Crow","name":"Jhon-Crow"},"closedAt":"2026-01-12T23:23:16Z","createdAt":"2026-01-12T22:38:04Z","labels":[],"number":82,"state":"CLOSED","title":"враг не должен лишаться возможности стрелять при отступлении"},{"author":{"id":"U_kgDOB_qn0g","is_bot":false,"login":"Jhon-Crow","name":"Jhon-Crow"},"closedAt":null,"createdAt":"2026-01-12T22:22:55Z","labels":[],"number":81,"state":"OPEN","title":"добавь агрессивное поведение врага после начала перезарядки игрока"},{"author":{"id":"U_kgDOB_qn0g","is_bot":false,"login":"Jhon-Crow","name":"Jhon-Crow"},"closedAt":null,"createdAt":"2026-01-12T22:14:15Z","labels":[],"number":79,"state":"OPEN","title":"убитые враги должны сразу игнорировать пули"},{"author":{"id":"U_kgDOB_qn0g","is_bot":false,"login":"Jhon-Crow","name":"Jhon-Crow"},"closedAt":"2026-01-12T22:28:49Z","createdAt":"2026-01-12T21:57:44Z","labels":[],"number":78,"state":"CLOSED","title":"fix сфера угрозы у врагов"},{"author":{"id":"U_kgDOB_qn0g","is_bot":false,"login":"Jhon-Crow","name":"Jhon-Crow"},"closedAt":"2026-01-12T22:12:16Z","createdAt":"2026-01-12T21:52:23Z","labels":[],"number":76,"state":"CLOSED","title":"подобрать оптимальную задержку реакции врагов"},{"author":{"id":"U_kgDOB_qn0g","is_bot":false,"login":"Jhon-Crow","name":"Jhon-Crow"},"closedAt":null,"createdAt":"2026-01-12T21:04:20Z","labels":[],"number":73,"state":"OPEN","title":"fix звуки стрельбы"},{"author":{"id":"U_kgDOB_qn0g","is_bot":false,"login":"Jhon-Crow","name":"Jhon-Crow"},"closedAt":null,"createdAt":"2026-01-12T20:58:13Z","labels":[],"number":72,"state":"OPEN","title":"fix пули"},{"author":{"id":"U_kgDOB_qn0g","is_bot":false,"login":"Jhon-Crow","name":"Jhon-Crow"},"closedAt":"2026-01-12T21:31:07Z","createdAt":"2026-01-12T20:49:56Z","labels":[],"number":71,"state":"CLOSED","title":"сделай тестовый уровень  зданием с комнатами и заллами"},{"author":{"id":"U_kgDOB_qn0g","is_bot":false,"login":"Jhon-Crow","name":"Jhon-Crow"},"closedAt":null,"createdAt":"2026-01-12T20:14:50Z","labels":[],"number":70,"state":"OPEN","title":"fix bug"},{"author":{"id":"U_kgDOB_qn0g","is_bot":false,"login":"Jhon-Crow","name":"Jhon-Crow"},"closedAt":null,"createdAt":"2026-01-12T19:59:03Z","labels":[],"number":69,"state":"OPEN","title":"добавь звук полной перезарядки m16 врагам"},{"author":{"id":"U_kgDOB_qn0g","is_bot":false,"login":"Jhon-Crow","name":"Jhon-Crow"},"closedAt":null,"createdAt":"2026-01-12T19:33:35Z","labels":[],"number":67,"state":"OPEN","title":"если игрок долго находится за одним укрытием враги организованно обходят с фланга"},{"author":{"id":"U_kgDOB_qn0g","is_bot":false,"login":"Jhon-Crow","name":"Jhon-Crow"},"closedAt":null,"createdAt":"2026-01-12T18:53:42Z","labels":[],"number":66,"state":"OPEN","title":"добавь направление взгляда врагам"},{"author":{"id":"U_kgDOB_qn0g","is_bot":false,"login":"Jhon-Crow","name":"Jhon-Crow"},"closedAt":null,"createdAt":"2026-01-12T18:11:18Z","labels":[],"number":64,"state":"OPEN","title":"добавь звук на нажатие кнопки b"},{"author":{"id":"U_kgDOB_qn0g","is_bot":false,"login":"Jhon-Crow","name":"Jhon-Crow"},"closedAt":"2026-01-12T18:36:12Z","createdAt":"2026-01-12T17:06:26Z","labels":[],"number":62,"state":"CLOSED","title":"fix enemise ai"},{"author":{"id":"U_kgDOB_qn0g","is_bot":false,"login":"Jhon-Crow","name":"Jhon-Crow"},"closedAt":"2026-01-12T17:15:25Z","createdAt":"2026-01-12T16:21:36Z","labels":[],"number":60,"state":"CLOSED","title":"fix reloading"},{"author":{"id":"U_kgDOB_qn0g","is_bot":false,"login":"Jhon-Crow","name":"Jhon-Crow"},"closedAt":null,"createdAt":"2026-01-12T15:58:30Z","labels":[],"number":59,"state":"OPEN","title":"fix когда игрок за укрытием враг не должен держать его \"на прицеле\""},{"author":{"id":"U_kgDOB_qn0g","is_bot":false,"login":"Jhon-Crow","name":"Jhon-Crow"},"closedAt":"2026-01-12T15:44:15Z","createdAt":"2026-01-12T15:32:13Z","labels":[],"number":56,"state":"CLOSED","title":"fix r -> f -> r reload"},{"author":{"id":"U_kgDOB_qn0g","is_bot":false,"login":"Jhon-Crow","name":"Jhon-Crow"},"closedAt":"2026-01-12T16:27:33Z","createdAt":"2026-01-12T14:55:31Z","labels":[],"number":55,"state":"CLOSED","title":"добавь звуки"},{"author":{"id":"U_kgDOB_qn0g","is_bot":false,"login":"Jhon-Crow","name":"Jhon-Crow"},"closedAt":null,"createdAt":"2026-01-12T14:42:26Z","labels":[],"number":53,"state":"OPEN","title":"добавить подсчёт очков после зачистки уровня"},{"author":{"id":"U_kgDOB_qn0g","is_bot":false,"login":"Jhon-Crow","name":"Jhon-Crow"},"closedAt":"2026-01-12T21:49:56Z","createdAt":"2026-01-12T14:32:43Z","labels":[],"number":52,"state":"CLOSED","title":"замедли скорость реакции врагов"},{"author":{"id":"U_kgDOB_qn0g","is_bot":false,"login":"Jhon-Crow","name":"Jhon-Crow"},"closedAt":"2026-01-12T14:45:45Z","createdAt":"2026-01-12T12:48:27Z","labels":[],"number":49,"state":"CLOSED","title":"добавь замедление времени при попадании"},{"author":{"id":"U_kgDOB_qn0g","is_bot":false,"login":"Jhon-Crow","name":"Jhon-Crow"},"closedAt":"2026-01-12T12:45:17Z","createdAt":"2026-01-12T12:06:05Z","labels":[],"number":46,"state":"CLOSED","title":"fix урон по игроку не идёт"},{"author":{"id":"U_kgDOB_qn0g","is_bot":false,"login":"Jhon-Crow","name":"Jhon-Crow"},"closedAt":"2026-01-12T12:20:35Z","createdAt":"2026-01-12T12:05:18Z","labels":[],"number":45,"state":"CLOSED","title":"fix enemies ai"},{"author":{"id":"U_kgDOB_qn0g","is_bot":false,"login":"Jhon-Crow","name":"Jhon-Crow"},"closedAt":null,"createdAt":"2026-01-12T11:29:15Z","labels":[],"number":44,"state":"OPEN","title":"fix enemies ai"},{"author":{"id":"U_kgDOB_qn0g","is_bot":false,"login":"Jhon-Crow","name":"Jhon-Crow"},"closedAt":"2026-01-12T12:03:41Z","createdAt":"2026-01-12T11:04:33Z","labels":[],"number":42,"state":"CLOSED","title":"настроить баланс и экономику"},{"author":{"id":"U_kgDOB_qn0g","is_bot":false,"login":"Jhon-Crow","name":"Jhon-Crow"},"closedAt":"2026-01-12T15:30:26Z","createdAt":"2026-01-12T10:19:19Z","labels":[],"number":41,"state":"CLOSED","title":"перезарядка игрока"},{"author":{"id":"U_kgDOB_qn0g","is_bot":false,"login":"Jhon-Crow","name":"Jhon-Crow"},"closedAt":"2026-01-12T09:51:36Z","createdAt":"2026-01-12T09:01:07Z","labels":[],"number":37,"state":"CLOSED","title":"усиль врагов"},{"author":{"id":"U_kgDOB_qn0g","is_bot":false,"login":"Jhon-Crow","name":"Jhon-Crow"},"closedAt":"2026-01-12T09:30:18Z","createdAt":"2026-01-12T08:31:27Z","labels":[],"number":35,"state":"CLOSED","title":"собери все реализованные функции в одну тестовую сцену"},{"author":{"id":"U_kgDOB_qn0g","is_bot":false,"login":"Jhon-Crow","name":"Jhon-Crow"},"closedAt":"2026-01-12T08:43:58Z","createdAt":"2026-01-12T08:29:03Z","labels":[],"number":33,"state":"CLOSED","title":"fix враги за укрытиями"},{"author":{"id":"U_kgDOB_qn0g","is_bot":false,"login":"Jhon-Crow","name":"Jhon-Crow"},"closedAt":"2026-01-12T00:04:35Z","createdAt":"2026-01-11T23:52:06Z","labels":[],"number":30,"state":"CLOSED","title":"fix enemies"},{"author":{"id":"U_kgDOB_qn0g","is_bot":false,"login":"Jhon-Crow","name":"Jhon-Crow"},"closedAt":"2026-01-11T23:36:26Z","createdAt":"2026-01-11T23:26:14Z","labels":[],"number":27,"state":"CLOSED","title":"fix лазер"},{"author":{"id":"U_kgDOB_qn0g","is_bot":false,"login":"Jhon-Crow","name":"Jhon-Crow"},"closedAt":"2026-01-11T22:27:37Z","createdAt":"2026-01-11T22:13:17Z","labels":[],"number":23,"state":"CLOSED","title":"fix TestTier не запускается"},{"author":{"id":"U_kgDOB_qn0g","is_bot":false,"login":"Jhon-Crow","name":"Jhon-Crow"},"closedAt":"2026-01-11T22:18:02Z","createdAt":"2026-01-11T22:09:34Z","labels":[],"number":21,"state":"CLOSED","title":"fix enemies"},{"author":{"id":"U_kgDOB_qn0g","is_bot":false,"login":"Jhon-Crow","name":"Jhon-Crow"},"closedAt":"2026-01-11T22:08:20Z","createdAt":"2026-01-11T21:58:03Z","labels":[],"number":19,"state":"CLOSED","title":"update scene"}]
